trytond/modules/health_archives/COPYING
trytond/modules/health_archives/README.rst
trytond/modules/health_archives/__init__.py
trytond/modules/health_archives/health_archives.py
trytond/modules/health_archives/health_archives_view.xml
trytond/modules/health_archives/icons/archives.svg
trytond/modules/health_archives/locale/ar.po
trytond/modules/health_archives/locale/de.po
trytond/modules/health_archives/locale/el.po
trytond/modules/health_archives/locale/eo.po
trytond/modules/health_archives/locale/es.po
trytond/modules/health_archives/locale/fr.po
trytond/modules/health_archives/locale/health_archives.pot
trytond/modules/health_archives/locale/it_IT.po
trytond/modules/health_archives/locale/ja_JP.po
trytond/modules/health_archives/locale/ka.po
trytond/modules/health_archives/locale/lo.po
trytond/modules/health_archives/locale/pt_BR.po
trytond/modules/health_archives/locale/sv.po
trytond/modules/health_archives/locale/tr.po
trytond/modules/health_archives/locale/uk.po
trytond/modules/health_archives/locale/zh_CN.po
trytond/modules/health_archives/pyproject.toml
trytond/modules/health_archives/tests/__init__.py
trytond/modules/health_archives/tests/test_health_archives.py
trytond/modules/health_archives/tryton.cfg
trytond/modules/health_archives/view/gnuhealth_paper_archive_form.xml
trytond/modules/health_archives/view/gnuhealth_paper_archive_tree.xml
gnuhealth_archives-5.0.2.dist-info/METADATA
gnuhealth_archives-5.0.2.dist-info/WHEEL
gnuhealth_archives-5.0.2.dist-info/licenses/COPYING
gnuhealth_archives-5.0.2.dist-info/RECORD
